asqlite3/__init__.py
asqlite3/asqlite3.py
py_asqlite3-0.7.dist-info/LICENCE
py_asqlite3-0.7.dist-info/METADATA
py_asqlite3-0.7.dist-info/WHEEL
py_asqlite3-0.7.dist-info/top_level.txt
py_asqlite3-0.7.dist-info/RECORD
